argle/__init__.py
argle/_old.py
argle/bargparse.py
argle/constants.py
argle/errors.py
argle/grammar.py
argle/new_grammar.py
argle/parser.py
argle/version.py
argle-0.4.0.dist-info/licenses/LICENSE
argle-0.4.0.dist-info/METADATA
argle-0.4.0.dist-info/WHEEL
argle-0.4.0.dist-info/top_level.txt
argle-0.4.0.dist-info/RECORD
